cappy239/__init__.py
cappy239/__version__.py
cappy239/cappy239.py
cappy239-0.1.13.dist-info/METADATA
cappy239-0.1.13.dist-info/WHEEL
cappy239-0.1.13.dist-info/top_level.txt
cappy239-0.1.13.dist-info/RECORD
