Metadata-Version: 2.1
Name: cappy239
Version: 0.1.13
Summary: Algorithms Computational Mathematics I: Spectral Analysis of Stochastic Processes taught by Dr Reinaldo Roberto Rosa at National Institute for Spacial Research (INPE).
Home-page: https://github.com/AdrianoPereira/cappy239
Author: Adriano P. Almeida
Author-email: adriano.almeida@inpe.br
License: MIT
Platform: UNKNOWN
Requires-Python: !=3.0.*, !=3.1.*, !=3.2.*, !=3.3.*
Requires-Dist: numpy (>=1.15.2)
Requires-Dist: matplotlib (>=3.1.0)
